setup.cfg
setup.py
resin/__init__.py
resin/auth.py
resin/base_request.py
resin/exceptions.py
resin/logs.py
resin/resources.py
resin/settings.py
resin/twofactor_auth.py
resin/models/__init__.py
resin/models/api_key.py
resin/models/application.py
resin/models/config.py
resin/models/config_variable.py
resin/models/device.py
resin/models/device_os.py
resin/models/environment_variables.py
resin/models/image.py
resin/models/key.py
resin/models/release.py
resin/models/service.py
resin/models/service_install.py
resin/models/supervisor.py
resin/models/tag.py
resin/util/__init__.py
resin/util/deprecation_warning.py
resin_sdk.egg-info/PKG-INFO
resin_sdk.egg-info/SOURCES.txt
resin_sdk.egg-info/dependency_links.txt
resin_sdk.egg-info/requires.txt
resin_sdk.egg-info/top_level.txt