Metadata-Version: 1.1
Name: resin-sdk
Version: 5.1.3
Summary: Resin.io SDK for Python
Home-page: https://github.com/resin-io/resin-sdk-python
Author: Resin IO
Author-email: info@resin.io
License: MIT
Keywords: resin api sdk
Platform: UNKNOWN
Classifier: Development Status :: 3 - Alpha
Classifier: Intended Audience :: Developers
Classifier: Topic :: Software Development :: Build Tools
Classifier: License :: OSI Approved :: MIT License
Classifier: Programming Language :: Python :: 2
Classifier: Programming Language :: Python :: 2.7
Classifier: Programming Language :: Python :: 3
Classifier: Programming Language :: Python :: 3.5
Classifier: Programming Language :: Python :: 3.6
